noti_py/__init__.py
noti_py/config/__init__.py
noti_py/config/config.py
noti_py/noti.py
noti.py-0.4.0.dist-info/entry_points.txt
noti.py-0.4.0.dist-info/LICENSE
noti.py-0.4.0.dist-info/WHEEL
noti.py-0.4.0.dist-info/METADATA
noti.py-0.4.0.dist-info/RECORD
