Metadata-Version: 2.1
Name: noti.py
Version: 0.4.0
Summary: Python-based notification script to post a message to a materix server via the Matrix client/server API
Home-page: https://github.com/kellya/notipy
License: MIT
Author: Alex Kelly
Author-email: kellya@arachnitech.com
Requires-Python: >=3.9,<4.0
Classifier: License :: OSI Approved :: MIT License
Classifier: Programming Language :: Python :: 3
Classifier: Programming Language :: Python :: 3.10
Classifier: Programming Language :: Python :: 3.9
Requires-Dist: PyYAML (>=5.4.1,<6.0.0)
Requires-Dist: click (>=8.0.1,<9.0.0)
Requires-Dist: coverage (>=5.5,<6.0)
Requires-Dist: requests (>=2.26.0,<3.0.0)
